Metadata-Version: 1.1
Name: numa
Version: 1.4.6
Summary: Interface to numa(3) Linux API for Python
Home-page: http://github.com/smira/py-numa
Author: Andrey Smirnov
Author-email: me@smira.ru
License: MIT
Platform: any
Classifier: Development Status :: 3 - Alpha
Classifier: License :: OSI Approved :: MIT License
Classifier: Operating System :: POSIX :: Linux
